gitsherlock/__init__.py
gitsherlock/__main__.py
gitsherlock/bitbucket.py
gitsherlock/github.py
gitsherlock-0.5.dist-info/LICENSE
gitsherlock-0.5.dist-info/METADATA
gitsherlock-0.5.dist-info/WHEEL
gitsherlock-0.5.dist-info/entry_points.txt
gitsherlock-0.5.dist-info/top_level.txt
gitsherlock-0.5.dist-info/RECORD
